{
  "id": "nowy_Z_Pluton__5_Pluton_N_20250829203534",
  "nation": "Niemcy",
  "unitType": "Z",
  "unitSize": "Pluton",
  "shape": "prostokąt",
  "label": "nowy_5_N_Z_Pluton",
  "unit_full_name": "Niemcy Zaopatrzenie Pluton ***",
  "move": 3,
  "attack": {
    "range": 1,
    "value": 1
  },
  "combat_value": 4,
  "defense_value": 2,
  "maintenance": 2,
  "price": 16,
  "sight": 2,
  "owner": "5",
  "image": "assets/tokens/nowe_dla_5/nowy_Z_Pluton__5_Pluton_N_20250829203534/token.png",
  "w": 240,
  "h": 240
}