{
  "id": "P_Pluton__6_Sch_tzen_Kompanie_20250703213835",
  "nation": "Niemcy",
  "unitType": "P",
  "unitSize": "Pluton",
  "shape": "prostokąt",
  "label": "6. Schützen Kompanie",
  "unit_full_name": "Niemcy Piechota Pluton ***",
  "move": 7,
  "attack": {
    "range": 2,
    "value": 6
  },
  "combat_value": 8,
  "defense_value": 7,
  "maintenance": 10,
  "price": 35,
  "sight": 3,
  "owner": "6 (Niemcy)",
  "image": "assets/tokens/Niemcy/P_Pluton__6_Sch_tzen_Kompanie_20250703213835/token.png",
  "w": 240,
  "h": 240
}